{
  "$schema": "https://schemas.wp.org/trunk/block.json",
  "apiVersion": 3,
  "name": "ria/feature-grid",
  "title": "RIA Feature Grid",
  "category": "ria-blocks",
  "icon": "grid-view",
  "description": "Responsive grid container for displaying Icon Boxes, Number Boxes, or Cards",
  "keywords": [
    "grid",
    "features",
    "layout",
    "container"
  ],
  "supports": {
    "html": false,
    "align": [
      "wide",
      "full"
    ],
    "spacing": {
      "margin": true,
      "padding": true
    }
  },
  "attributes": {
    "columns": {
      "type": "number",
      "default": 3
    },
    "columnGap": {
      "type": "number",
      "default": 24
    },
    "rowGap": {
      "type": "number",
      "default": 24
    },
    "contentAlignment": {
      "type": "string",
      "default": "center"
    },
    "verticalAlignment": {
      "type": "string",
      "default": "top"
    },
    "animationEnabled": {
      "type": "boolean",
      "default": true
    },
    "animationType": {
      "type": "string",
      "default": "fadeInUp"
    },
    "animationDuration": {
      "type": "number",
      "default": 0.6
    },
    "animationDelay": {
      "type": "number",
      "default": 0
    },
    "animationEasing": {
      "type": "string",
      "default": "ease-out"
    },
    "hoverAnimation": {
      "type": "string",
      "default": "none"
    }
  },
  "textdomain": "ria",
  "editorScript": "file:./index.js",
  "editorStyle": "file:./index.css",
  "style": "file:./style-index.css"
}
